{
  "title": "Greenter Xmldsig",
  "description": "Tool for sign xml.",
  "difficulty": "beginner",
  "time": "2 minutes",
  "details": {
    "steps": [{
      "title": "Paso 1 - Install Xmldsig",
      "text": "step1.md"
    },{
      "title": "Paso 2 - Run Sample",
      "text": "step2.md"
    }],
    "intro": {
      "text": "intro.md",
      "credits": "https://github.com/giansalex",
      "courseData": "php.sh"
    },
    "finish": {
      "text": "finish.md"
    },
    "assets": {
      "client": [
        {
          "file": "assets/*",
          "target": "/root"
        }
      ]
    }
  },
  "environment": {
    "icon": "fa-php",
    "showdashboard": true,
    "uilayout": "editor-terminal",
    "uimessage1": "\u001b[32mTerminal con Php.\u001b[m\r\n",
    "uisettings": "php"
  },
  "backend": {
    "imageid": "ubuntu"
  }
}
